pynterpol.py
pynterpol-1.1.0.dist-info/LICENSE
pynterpol-1.1.0.dist-info/METADATA
pynterpol-1.1.0.dist-info/WHEEL
pynterpol-1.1.0.dist-info/top_level.txt
pynterpol-1.1.0.dist-info/RECORD
